README.md
setup.py
ntfb/__init__.py
ntfb/notify_bot.py
ntfb.egg-info/PKG-INFO
ntfb.egg-info/SOURCES.txt
ntfb.egg-info/dependency_links.txt
ntfb.egg-info/top_level.txt